kubetables.py
kubetables-0.6.data/scripts/kubetables.py
kubetables-0.6.dist-info/LICENSE.txt
kubetables-0.6.dist-info/METADATA
kubetables-0.6.dist-info/WHEEL
kubetables-0.6.dist-info/top_level.txt
kubetables-0.6.dist-info/RECORD
